LICENSE
MANIFEST.in
README.rst
setup.py
django_radio.egg-info/PKG-INFO
django_radio.egg-info/SOURCES.txt
django_radio.egg-info/dependency_links.txt
django_radio.egg-info/not-zip-safe
django_radio.egg-info/requires.txt
django_radio.egg-info/top_level.txt
radio/__init__.py
radio/global_vars.py
radio/settings.py
radio/settings_base.py
radio/urls.py
radio/wsgi.py
radio/apps/__init__.py
radio/apps/dashboard/__init__.py
radio/apps/dashboard/forms.py
radio/apps/dashboard/urls.py
radio/apps/dashboard/views.py
radio/apps/dashboard/templates/dashboard/base_site.html
radio/apps/dashboard/templates/dashboard/fullcalendar.html
radio/apps/dashboard/templates/dashboard/fullcalendar_error.html
radio/apps/dashboard/templates/dashboard/item_edit_form.html
radio/apps/dashboard/templates/dashboard/item_edit_form_success.html
radio/apps/programmes/__init__.py
radio/apps/programmes/admin.py
radio/apps/programmes/feeds.py
radio/apps/programmes/models.py
radio/apps/programmes/tests.py
radio/apps/programmes/urls.py
radio/apps/programmes/views.py
radio/apps/programmes/migrations/0001_initial.py
radio/apps/programmes/migrations/0002_change_language_choices.py
radio/apps/programmes/migrations/0003_change_textfield_to_richtextfield.py
radio/apps/programmes/migrations/0004_change_photo_url.py
radio/apps/programmes/migrations/__init__.py
radio/apps/programmes/templates/programmes/episode_detail.html
radio/apps/programmes/templates/programmes/programme_detail.html
radio/apps/programmes/templates/programmes/programme_list.html
radio/apps/programmes/templates/programmes/staff_list_snippet.html
radio/apps/schedules/__init__.py
radio/apps/schedules/admin.py
radio/apps/schedules/models.py
radio/apps/schedules/tests.py
radio/apps/schedules/urls.py
radio/apps/schedules/views.py
radio/apps/schedules/migrations/0001_initial.py
radio/apps/schedules/migrations/__init__.py
radio/apps/schedules/templates/schedules/schedules_list.html
radio/apps/users/__init__.py
radio/apps/users/admin.py
radio/apps/users/models.py
radio/apps/users/tests.py
radio/apps/users/urls.py
radio/apps/users/views.py
radio/apps/users/migrations/0001_initial.py
radio/apps/users/migrations/0002_change_textfield_to_richtextfield.py
